teju/__init__.py
teju-0.0.1.dist-info/METADATA
teju-0.0.1.dist-info/WHEEL
teju-0.0.1.dist-info/top_level.txt
teju-0.0.1.dist-info/RECORD
